[
  {
    "formattedHour": "11:39:44",
    "titleWithLink": "[转拽 砖 转拽砖专转  砖专转. ''转 注砖 转 砖专转  注 转 砖专,  转住专 砖转 专砖, 专转 爪 专专 转拽砖专转](https://rotter.net/forum/scoops1/859485.shtml)",
    "title": "转拽 砖 转拽砖专转  砖专转. ''转 注砖 转 砖专转  注 转 砖专,  转住专 砖转 专砖, 专转 爪 专专 转拽砖专转"
  },
  {
    "formattedHour": "11:50:12",
    "titleWithLink": "[注专 拽专  转-](https://rotter.net/forum/scoops1/859486.shtml)",
    "title": "注专 拽专  转-"
  },
  {
    "formattedHour": "11:51:58",
    "titleWithLink": "['' 爪 住转 爪注: 驻转专 住拽爪转 专拽转 爪注转 拽 砖专.](https://rotter.net/forum/scoops1/859487.shtml)",
    "title": "'' 爪 住转 爪注: 驻转专 住拽爪转 专拽转 爪注转 拽 砖专."
  },
  {
    "formattedHour": "11:57:48",
    "titleWithLink": "[ㄗψ注  (11:56): 注, 砖转](https://rotter.net/forum/scoops1/859488.shtml)",
    "title": "爪注  (11:56): 注, 砖转"
  }
]