[
  {
    "formattedHour": "11:59:08",
    "titleWithLink": "[ㄗψ注  (11:57): 拽抓 ](https://rotter.net/forum/scoops1/858643.shtml)",
    "title": "爪注  (11:57): 拽抓 "
  },
  {
    "formattedHour": "13:36:40",
    "titleWithLink": "[专'' 专 砖  专住  注 专驻拽转 - 注 专砖 拽转](https://rotter.net/forum/scoops1/858644.shtml)",
    "title": "专'' 专 砖  专住  注 专驻拽转 - 注 专砖 拽转"
  },
  {
    "formattedHour": "13:46:48",
    "titleWithLink": "[ : 专 转拽祝 驻专 专 , -5 拽状 爪驻转 ](https://rotter.net/forum/scoops1/858645.shtml)",
    "title": " : 专 转拽祝 驻专 专 , -5 拽状 爪驻转 "
  },
  {
    "formattedHour": "14:01:58",
    "titleWithLink": "[转  砖拽  住拽爪转 注 砖专 住专抓'  专](https://rotter.net/forum/scoops1/858646.shtml)",
    "title": "转  砖拽  住拽爪转 注 砖专 住专抓'  专"
  }
]